{
  "ticket_id": "OMN-8246",
  "summary": "BaselinesROICard component with delta metrics",
  "status": "verified",
  "total_checks": 3,
  "verified_count": 3,
  "failed_count": 0,
  "checks": [
    {
      "evidence_id": "dod-001",
      "description": "Shows loading state initially",
      "status": "verified",
      "message": "Part 3 implementation complete"
    },
    {
      "evidence_id": "dod-002",
      "description": "Renders -12,500 token delta and 4 promote count",
      "status": "verified",
      "message": "Part 3 implementation complete"
    },
    {
      "evidence_id": "dod-003",
      "description": "Shows empty state when API returns null",
      "status": "verified",
      "message": "Part 3 implementation complete"
    }
  ],
  "generated_at": "2026-04-10T18:25:55.376181+00:00"
}
